MANIFEST.in
README.rst
setup.py
fanny.egg-info/PKG-INFO
fanny.egg-info/SOURCES.txt
fanny.egg-info/dependency_links.txt
fanny.egg-info/top_level.txt
myfact/__init__.py
myfact/fact.py