Metadata-Version: 1.0
Name: fanny
Version: 0.1
Summary: Factorial module.
Home-page: http://pymbook.readthedocs.org/en/latest/
Author: Kushal Das
Author-email: kushaldas@gmail.com
License: MIT
Platform: Linux
